rw_source/ReadSource.py
rw_source/WriteSource.py
rw_source/__init__.py
rw_source-0.1.dist-info/METADATA
rw_source-0.1.dist-info/WHEEL
rw_source-0.1.dist-info/top_level.txt
rw_source-0.1.dist-info/RECORD
