Metadata-Version: 2.1
Name: rw-source
Version: 0.1
Summary: read write source
Author: Nazar
